{
  "$schema": "https://developer.microsoft.com/json-schemas/fabric/item/report/definition/visualContainer/2.6.0/schema.json",
  "name": "1e25ffeb50f9f65d473a",
  "position": {
    "x": 0,
    "y": 360.42430086788812,
    "z": 2000,
    "height": 348.08100289296044,
    "width": 123.43297974927675,
    "tabOrder": 2000
  },
  "visual": {
    "visualType": "slicer",
    "query": {
      "queryState": {
        "Values": {
          "projections": [
            {
              "field": {
                "Column": {
                  "Expression": {
                    "SourceRef": {
                      "Entity": "Design Attributes"
                    }
                  },
                  "Property": "Design Attributes"
                }
              },
              "queryRef": "Scanned Attributes.Scanned Attributes",
              "nativeQueryRef": "Design Attributes",
              "active": true
            }
          ]
        }
      }
    },
    "objects": {
      "general": [
        {
          "properties": {
            "orientation": {
              "expr": {
                "Literal": {
                  "Value": "1D"
                }
              }
            },
            "filter": {
              "filter": {
                "Version": 2,
                "From": [
                  {
                    "Name": "d",
                    "Entity": "Design Attributes",
                    "Type": 0
                  }
                ],
                "Where": [
                  {
                    "Condition": {
                      "In": {
                        "Expressions": [
                          {
                            "Column": {
                              "Expression": {
                                "SourceRef": {
                                  "Source": "d"
                                }
                              },
                              "Property": "Design Attributes Fields"
                            }
                          }
                        ],
                        "Values": [
                          [
                            {
                              "Literal": {
                                "Value": "'''Page Scans''[Visuals/Page]'"
                              }
                            }
                          ]
                        ]
                      }
                    },
                    "Annotations": {
                      "filterExpressionMetadata": {
                        "expressions": [
                          {
                            "Column": {
                              "Expression": {
                                "SourceRef": {
                                  "Entity": "Design Attributes"
                                }
                              },
                              "Property": "Design Attributes"
                            }
                          }
                        ],
                        "decomposedIdentities": {
                          "values": [
                            [
                              {
                                "0": [
                                  {
                                    "Literal": {
                                      "Value": "'''Page Scans''[Visuals/Page]'"
                                    }
                                  }
                                ]
                              }
                            ]
                          ],
                          "columns": [
                            {
                              "value": {
                                "Column": {
                                  "Expression": {
                                    "SourceRef": {
                                      "Entity": "Design Attributes"
                                    }
                                  },
                                  "Property": "Design Attributes Fields"
                                }
                              }
                            }
                          ]
                        },
                        "valueMap": [
                          {
                            "0": "Visuals per Page"
                          }
                        ]
                      }
                    }
                  }
                ]
              }
            }
          }
        }
      ],
      "selection": [
        {
          "properties": {
            "selectAllCheckboxEnabled": {
              "expr": {
                "Literal": {
                  "Value": "true"
                }
              }
            },
            "singleSelect": {
              "expr": {
                "Literal": {
                  "Value": "false"
                }
              }
            },
            "strictSingleSelect": {
              "expr": {
                "Literal": {
                  "Value": "true"
                }
              }
            }
          }
        }
      ],
      "header": [
        {
          "properties": {
            "show": {
              "expr": {
                "Literal": {
                  "Value": "false"
                }
              }
            },
            "textSize": {
              "expr": {
                "Literal": {
                  "Value": "12D"
                }
              }
            }
          }
        }
      ],
      "items": [
        {
          "properties": {
            "textSize": {
              "expr": {
                "Literal": {
                  "Value": "8D"
                }
              }
            }
          }
        }
      ],
      "data": [
        {
          "properties": {
            "mode": {
              "expr": {
                "Literal": {
                  "Value": "'Basic'"
                }
              }
            }
          }
        }
      ]
    },
    "visualContainerObjects": {
      "title": [
        {
          "properties": {
            "show": {
              "expr": {
                "Literal": {
                  "Value": "false"
                }
              }
            },
            "heading": {
              "expr": {
                "Literal": {
                  "Value": "'Normal'"
                }
              }
            },
            "titleWrap": {
              "expr": {
                "Literal": {
                  "Value": "true"
                }
              }
            },
            "fontColor": {
              "solid": {
                "color": {
                  "expr": {
                    "Literal": {
                      "Value": "'#F8CF70'"
                    }
                  }
                }
              }
            },
            "background": {
              "solid": {
                "color": {
                  "expr": {
                    "Literal": {
                      "Value": "'#281649'"
                    }
                  }
                }
              }
            },
            "fontSize": {
              "expr": {
                "Literal": {
                  "Value": "12D"
                }
              }
            },
            "text": {
              "expr": {
                "Literal": {
                  "Value": "'Design attributes Slicer'"
                }
              }
            }
          }
        }
      ],
      "background": [
        {
          "properties": {
            "show": {
              "expr": {
                "Literal": {
                  "Value": "false"
                }
              }
            },
            "transparency": {
              "expr": {
                "Literal": {
                  "Value": "0D"
                }
              }
            }
          }
        }
      ],
      "general": [
        {
          "properties": {
            "keepLayerOrder": {
              "expr": {
                "Literal": {
                  "Value": "true"
                }
              }
            }
          }
        }
      ],
      "border": [
        {
          "properties": {
            "show": {
              "expr": {
                "Literal": {
                  "Value": "false"
                }
              }
            },
            "color": {
              "solid": {
                "color": {
                  "expr": {
                    "Literal": {
                      "Value": "'#281649'"
                    }
                  }
                }
              }
            },
            "radius": {
              "expr": {
                "Literal": {
                  "Value": "15D"
                }
              }
            }
          }
        }
      ],
      "dropShadow": [
        {
          "properties": {
            "show": {
              "expr": {
                "Literal": {
                  "Value": "false"
                }
              }
            }
          }
        }
      ],
      "visualHeader": [
        {
          "properties": {
            "show": {
              "expr": {
                "Literal": {
                  "Value": "false"
                }
              }
            }
          }
        }
      ],
      "padding": [
        {
          "properties": {
            "left": {
              "expr": {
                "Literal": {
                  "Value": "0D"
                }
              }
            },
            "top": {
              "expr": {
                "Literal": {
                  "Value": "0D"
                }
              }
            },
            "right": {
              "expr": {
                "Literal": {
                  "Value": "0D"
                }
              }
            },
            "bottom": {
              "expr": {
                "Literal": {
                  "Value": "0D"
                }
              }
            }
          }
        }
      ]
    },
    "syncGroup": {
      "groupName": "Design Attributes1",
      "fieldChanges": true,
      "filterChanges": true
    },
    "drillFilterOtherVisuals": true
  },
  "filterConfig": {
    "filters": [
      {
        "name": "2735f0a8f0ec0109c412",
        "field": {
          "Column": {
            "Expression": {
              "SourceRef": {
                "Entity": "Design Attributes"
              }
            },
            "Property": "Design Attributes"
          }
        },
        "type": "Categorical",
        "filter": {
          "Version": 2,
          "From": [
            {
              "Name": "d",
              "Entity": "Design Attributes",
              "Type": 0
            }
          ],
          "Where": [
            {
              "Condition": {
                "Not": {
                  "Expression": {
                    "In": {
                      "Expressions": [
                        {
                          "Column": {
                            "Expression": {
                              "SourceRef": {
                                "Source": "d"
                              }
                            },
                            "Property": "Design Attributes Fields"
                          }
                        }
                      ],
                      "Values": [
                        [
                          {
                            "Literal": {
                              "Value": "'''Reports''[Complexity Score]'"
                            }
                          }
                        ],
                        [
                          {
                            "Literal": {
                              "Value": "'''Reports''[Usability Score]'"
                            }
                          }
                        ],
                        [
                          {
                            "Literal": {
                              "Value": "'''Reports''[Passivity Score]'"
                            }
                          }
                        ],
                        [
                          {
                            "Literal": {
                              "Value": "'''PBI Measures''[Count of Measures]'"
                            }
                          }
                        ],
                        [
                          {
                            "Literal": {
                              "Value": "'''PBI Measures''[Measure Expression Length]'"
                            }
                          }
                        ],
                        [
                          {
                            "Literal": {
                              "Value": "'''PBI Columns''[Calculated Columns]'"
                            }
                          }
                        ],
                        [
                          {
                            "Literal": {
                              "Value": "'''PBI Columns''[Column Expression Length]'"
                            }
                          }
                        ],
                        [
                          {
                            "Literal": {
                              "Value": "'''Report Scans''[Bookmarks]'"
                            }
                          }
                        ]
                      ]
                    }
                  }
                }
              },
              "Annotations": {
                "filterExpressionMetadata": {
                  "expressions": [
                    {
                      "Column": {
                        "Expression": {
                          "SourceRef": {
                            "Entity": "Design Attributes"
                          }
                        },
                        "Property": "Design Attributes"
                      }
                    }
                  ],
                  "decomposedIdentities": {
                    "values": [
                      [
                        {
                          "0": [
                            {
                              "Literal": {
                                "Value": "'''Reports''[Complexity Score]'"
                              }
                            }
                          ]
                        }
                      ],
                      [
                        {
                          "0": [
                            {
                              "Literal": {
                                "Value": "'''Reports''[Usability Score]'"
                              }
                            }
                          ]
                        }
                      ],
                      [
                        {
                          "0": [
                            {
                              "Literal": {
                                "Value": "'''Reports''[Passivity Score]'"
                              }
                            }
                          ]
                        }
                      ],
                      [
                        {
                          "0": [
                            {
                              "Literal": {
                                "Value": "'''PBI Measures''[Count of Measures]'"
                              }
                            }
                          ]
                        }
                      ],
                      [
                        {
                          "0": [
                            {
                              "Literal": {
                                "Value": "'''PBI Measures''[Measure Expression Length]'"
                              }
                            }
                          ]
                        }
                      ],
                      [
                        {
                          "0": [
                            {
                              "Literal": {
                                "Value": "'''PBI Columns''[Calculated Columns]'"
                              }
                            }
                          ]
                        }
                      ],
                      [
                        {
                          "0": [
                            {
                              "Literal": {
                                "Value": "'''PBI Columns''[Column Expression Length]'"
                              }
                            }
                          ]
                        }
                      ],
                      [
                        {
                          "0": [
                            {
                              "Literal": {
                                "Value": "'''Report Scans''[Bookmarks]'"
                              }
                            }
                          ]
                        }
                      ]
                    ],
                    "columns": [
                      {
                        "value": {
                          "Column": {
                            "Expression": {
                              "SourceRef": {
                                "Entity": "Design Attributes"
                              }
                            },
                            "Property": "Design Attributes Fields"
                          }
                        }
                      }
                    ]
                  },
                  "valueMap": [
                    {
                      "0": "Complexity Score"
                    },
                    {
                      "0": "Usability Score"
                    },
                    {
                      "0": "Passivity Score"
                    },
                    {
                      "0": "# of Measures"
                    },
                    {
                      "0": "DAX Length"
                    },
                    {
                      "0": "# of Calculated Columns"
                    },
                    {
                      "0": "Calc Columns DAX Length"
                    },
                    {
                      "0": "# of Bookmarks"
                    }
                  ]
                }
              }
            }
          ]
        },
        "objects": {
          "general": [
            {
              "properties": {
                "isInvertedSelectionMode": {
                  "expr": {
                    "Literal": {
                      "Value": "true"
                    }
                  }
                }
              }
            }
          ]
        }
      }
    ]
  }
}