{
  "$schema": "https://developer.microsoft.com/json-schemas/fabric/item/report/definition/visualContainer/2.6.0/schema.json",
  "name": "4deb9fea5ede90626973",
  "position": {
    "x": 69.407092975489519,
    "y": 54.684376283719018,
    "z": 2000,
    "height": 59.94248938792277,
    "width": 1191.4884294125702,
    "tabOrder": 8000
  },
  "visual": {
    "visualType": "multiRowCard",
    "query": {
      "queryState": {
        "Values": {
          "projections": [
            {
              "field": {
                "Measure": {
                  "Expression": {
                    "SourceRef": {
                      "Entity": "Reports"
                    }
                  },
                  "Property": "Instrumented Reports"
                }
              },
              "queryRef": "Reports.Instrumented Reports",
              "nativeQueryRef": "Instrumented Reports"
            },
            {
              "field": {
                "Measure": {
                  "Expression": {
                    "SourceRef": {
                      "Entity": "Report Sessions"
                    }
                  },
                  "Property": "Opened Reports"
                }
              },
              "queryRef": "Report Sessions.Opened reports",
              "nativeQueryRef": "Opened Reports"
            },
            {
              "field": {
                "Measure": {
                  "Expression": {
                    "SourceRef": {
                      "Entity": "Report Sessions"
                    }
                  },
                  "Property": "Unused Reports"
                }
              },
              "queryRef": "Report Sessions.Unused reports",
              "nativeQueryRef": "Unused Reports"
            },
            {
              "field": {
                "Measure": {
                  "Expression": {
                    "SourceRef": {
                      "Entity": "Report Sessions"
                    }
                  },
                  "Property": "% Passive Reports"
                }
              },
              "queryRef": "Report Sessions.% Passive reports",
              "nativeQueryRef": "% Passive Reports"
            },
            {
              "field": {
                "Measure": {
                  "Expression": {
                    "SourceRef": {
                      "Entity": "Report Sessions"
                    }
                  },
                  "Property": "% Unused Reports"
                }
              },
              "queryRef": "Report Sessions.% Unused reports",
              "nativeQueryRef": "% Unused Reports"
            },
            {
              "field": {
                "Measure": {
                  "Expression": {
                    "SourceRef": {
                      "Entity": "Page Sessions"
                    }
                  },
                  "Property": "% Unused Pages"
                }
              },
              "queryRef": "Page Sessions.% Unused Pages",
              "nativeQueryRef": "% Unused Pages"
            }
          ]
        }
      },
      "sortDefinition": {
        "sort": [
          {
            "field": {
              "Measure": {
                "Expression": {
                  "SourceRef": {
                    "Entity": "Reports"
                  }
                },
                "Property": "Instrumented Reports"
              }
            },
            "direction": "Descending"
          }
        ],
        "isDefaultSort": true
      }
    },
    "objects": {
      "categoryLabels": [
        {
          "properties": {
            "show": {
              "expr": {
                "Literal": {
                  "Value": "true"
                }
              }
            },
            "fontSize": {
              "expr": {
                "Literal": {
                  "Value": "10D"
                }
              }
            }
          }
        }
      ],
      "dataLabels": [
        {
          "properties": {
            "fontSize": {
              "expr": {
                "Literal": {
                  "Value": "10D"
                }
              }
            }
          }
        }
      ],
      "card": [
        {
          "properties": {
            "barShow": {
              "expr": {
                "Literal": {
                  "Value": "false"
                }
              }
            }
          }
        }
      ]
    },
    "visualContainerObjects": {
      "title": [
        {
          "properties": {
            "text": {
              "expr": {
                "Literal": {
                  "Value": "'Metrics'"
                }
              }
            },
            "show": {
              "expr": {
                "Literal": {
                  "Value": "false"
                }
              }
            },
            "heading": {
              "expr": {
                "Literal": {
                  "Value": "'Heading2'"
                }
              }
            },
            "titleWrap": {
              "expr": {
                "Literal": {
                  "Value": "true"
                }
              }
            }
          }
        }
      ],
      "background": [
        {
          "properties": {
            "show": {
              "expr": {
                "Literal": {
                  "Value": "true"
                }
              }
            },
            "transparency": {
              "expr": {
                "Literal": {
                  "Value": "0D"
                }
              }
            }
          }
        }
      ],
      "border": [
        {
          "properties": {
            "show": {
              "expr": {
                "Literal": {
                  "Value": "true"
                }
              }
            },
            "color": {
              "solid": {
                "color": {
                  "expr": {
                    "Literal": {
                      "Value": "'#281649'"
                    }
                  }
                }
              }
            },
            "radius": {
              "expr": {
                "Literal": {
                  "Value": "15D"
                }
              }
            }
          }
        }
      ],
      "dropShadow": [
        {
          "properties": {
            "show": {
              "expr": {
                "Literal": {
                  "Value": "true"
                }
              }
            },
            "color": {
              "solid": {
                "color": {
                  "expr": {
                    "Literal": {
                      "Value": "'#b3b3b3'"
                    }
                  }
                }
              }
            }
          }
        }
      ],
      "spacing": [
        {
          "properties": {
            "customizeSpacing": {
              "expr": {
                "Literal": {
                  "Value": "true"
                }
              }
            },
            "spaceBelowTitle": {
              "expr": {
                "Literal": {
                  "Value": "10D"
                }
              }
            }
          }
        }
      ],
      "subTitle": [
        {
          "properties": {
            "text": {
              "expr": {
                "Literal": {
                  "Value": "'aaa'"
                }
              }
            },
            "show": {
              "expr": {
                "Literal": {
                  "Value": "true"
                }
              }
            }
          }
        }
      ],
      "visualHeader": [
        {
          "properties": {
            "show": {
              "expr": {
                "Literal": {
                  "Value": "false"
                }
              }
            }
          }
        }
      ]
    },
    "drillFilterOtherVisuals": true
  }
}